stringenum/__init__.py
stringenum/_compat.py
stringenum/_core.py
stringenum/py.typed
stringenum-0.6.0.dist-info/METADATA
stringenum-0.6.0.dist-info/WHEEL
stringenum-0.6.0.dist-info/licenses/LICENSE
stringenum-0.6.0.dist-info/RECORD
