Metadata-Version: 2.4
Name: stringenum
Version: 0.6.0
Summary: A small, dependency-free library offering additional enum.StrEnum subclasses and a backport for older Python versions.
Project-URL: Repository, https://github.com/Ravencentric/stringenum
Author-email: Ravencentric <me@ravencentric.cc>
License-Expression: MIT
License-File: LICENSE
Keywords: enum,strenum
Classifier: Intended Audience :: Developers
Classifier: Operating System :: OS Independent
Classifier: Programming Language :: Python :: 3.9
Classifier: Programming Language :: Python :: 3.10
Classifier: Programming Language :: Python :: 3.11
Classifier: Programming Language :: Python :: 3.12
Classifier: Programming Language :: Python :: 3.13
Classifier: Typing :: Typed
Requires-Python: >=3.9
